README.md
setup.cfg
setup.py
leolabs/__init__.py
leolabs.egg-info/PKG-INFO
leolabs.egg-info/SOURCES.txt
leolabs.egg-info/dependency_links.txt
leolabs.egg-info/entry_points.txt
leolabs.egg-info/requires.txt
leolabs.egg-info/top_level.txt
leolabs/bin/__init__.py
leolabs/bin/cli.py
leolabs/cli/__init__.py
leolabs/cli/commands.py
leolabs/cli/utils.py