Metadata-Version: 1.0
Name: leolabs
Version: 0.1.21
Summary: LeoLabs Api
Home-page: https://github.com/leolabs-space/leo-api-python
Author: LeoLabs, Inc.
Author-email: support@leolabs.space
License: UNKNOWN
Keywords: leolabs,radar,space,leo,orbit,propagation,norad
Platform: UNKNOWN
